MANIFEST.in
README.md
README.rst
setup.py
django_graphiql/__init__.py
django_graphiql/urls.py
django_graphiql/views.py
django_graphiql.egg-info/PKG-INFO
django_graphiql.egg-info/SOURCES.txt
django_graphiql.egg-info/dependency_links.txt
django_graphiql.egg-info/not-zip-safe
django_graphiql.egg-info/requires.txt
django_graphiql.egg-info/top_level.txt
django_graphiql/static/graphiql/.DS_Store
django_graphiql/static/graphiql/fetch.min.js
django_graphiql/static/graphiql/graphiql.css
django_graphiql/static/graphiql/graphiql.min.js
django_graphiql/static/graphiql/react-dom.min.js
django_graphiql/static/graphiql/react.min.js
django_graphiql/templates/graphiql/index.html