Metadata-Version: 1.1
Name: django-graphiql
Version: 0.4.2
Summary: Integrate GraphiQL easily into your Django project
Home-page: http://github.com/graphql-python/django-graphiql
Author: Syrus Akbary
Author-email: me@syrusakbary.com
License: MIT
Download-URL: git@github.com:graphql-python/django-graphiql.git
Keywords: django graphiql graphql graphene graphql-core
Platform: any
